fastnanoid-0.4.3.dist-info/METADATA
fastnanoid-0.4.3.dist-info/WHEEL
fastnanoid-0.4.3.dist-info/licenses/LICENSE
fastnanoid/__init__.py
fastnanoid/fastnanoid.cpython-313-s390x-linux-gnu.so
fastnanoid/fastnanoid.pyi
fastnanoid/py.typed
fastnanoid/uuid.py
fastnanoid-0.4.3.dist-info/RECORD
