Metadata-Version: 2.4
Name: fastnanoid
Version: 0.4.3
Classifier: Intended Audience :: Developers
Classifier: Programming Language :: Rust
Classifier: Programming Language :: Python :: Implementation :: CPython
Classifier: Programming Language :: Python :: Implementation :: PyPy
Classifier: Programming Language :: Python :: 3
Classifier: Programming Language :: Python :: 3 :: Only
Classifier: Programming Language :: Python :: 3.8
Classifier: Programming Language :: Python :: 3.9
Classifier: Programming Language :: Python :: 3.10
Classifier: Programming Language :: Python :: 3.11
Classifier: Programming Language :: Python :: 3.12
Classifier: Programming Language :: Python :: 3.13
Classifier: Operating System :: OS Independent
Classifier: License :: OSI Approved :: MIT License
Classifier: Typing :: Typed
License-File: LICENSE
Summary: A tiny, secure URL-friendly, and fast unique string ID generator for Python, written in Rust.
Keywords: nanoid
Author-email: Oliver Lambson <oliverlambson@gmail.com>, Ochir Erkhembayar <oliverlambson@gmail.com>
Maintainer-email: Oliver Lambson <oliverlambson@gmail.com>
Requires-Python: >=3.8
Project-URL: Homepage, https://github.com/oliverlambson/fastnanoid
Project-URL: Issues, https://github.com/oliverlambson/fastnanoid/issues
